hypnospy/__init__.py
hypnospy/diary.py
hypnospy/experiment.py
hypnospy/misc.py
hypnospy/wearable.py
hypnospy/analysis/__init__.py
hypnospy/analysis/circadian_analysis.py
hypnospy/analysis/non_wearing_detector.py
hypnospy/analysis/phyisical_activity.py
hypnospy/analysis/sleep_boundary_detector.py
hypnospy/analysis/sleep_metrics.py
hypnospy/analysis/sleep_wake_analysis.py
hypnospy/analysis/validator.py
hypnospy/analysis/visualization.py
hypnospy/data/__init__.py
hypnospy/data/preprocessing.py
tests/__init__.py
tests/test_preprocessing.py
tests/test_time_series_processing.py
tests/test_wearable.py
hypnospy-0.0.3.dist-info/LICENSE
hypnospy-0.0.3.dist-info/METADATA
hypnospy-0.0.3.dist-info/WHEEL
hypnospy-0.0.3.dist-info/top_level.txt
hypnospy-0.0.3.dist-info/RECORD
