Metadata-Version: 2.1
Name: hypnospy
Version: 0.0.3
Summary: A Device-Agnostic, Open-Source Python Software for Wearable Circadian Rhythm and Sleep Analysis and Visualization
Home-page: https://github.com/ippozuelo/HypnosPy/
Author: Ignacio Pozuelo, Joao Palotti
Author-email: ignacio_perez_pozuelo@alumni.brown.edu, joaopalotti@gmail.com
License: BSD
Platform: UNKNOWN
Requires-Python: >=3.6
Requires-Dist: pandas (>=1.0.1)
Requires-Dist: numpy (>=1.0.0)
Requires-Dist: scipy (>=1.1.0)
Requires-Dist: matplotlib (>=1.5)
Requires-Dist: seaborn (>=0.11.0)
